cargo_lambda_cdk/__init__.py
cargo_lambda_cdk/py.typed
cargo_lambda_cdk/_jsii/__init__.py
cargo_lambda_cdk/_jsii/cargo-lambda-cdk@0.0.36.jsii.tgz
cargo_lambda_cdk-0.0.36.dist-info/LICENSE
cargo_lambda_cdk-0.0.36.dist-info/METADATA
cargo_lambda_cdk-0.0.36.dist-info/WHEEL
cargo_lambda_cdk-0.0.36.dist-info/top_level.txt
cargo_lambda_cdk-0.0.36.dist-info/RECORD
